kafka_logger/__init__.py
kafka_logger/handlers.py
tests/__init__.py
tests/test_handlers.py
kafka_logging_handler-0.2.5.dist-info/LICENSE
kafka_logging_handler-0.2.5.dist-info/METADATA
kafka_logging_handler-0.2.5.dist-info/WHEEL
kafka_logging_handler-0.2.5.dist-info/top_level.txt
kafka_logging_handler-0.2.5.dist-info/RECORD
