Metadata-Version: 2.1
Name: kafka-logging-handler
Version: 0.2.5
Summary: A Python logging handler library for Kafka consumers.
Home-page: https://github.com/redhat-aqe/kafka-logging-handler
Author: Mark Birger, Michaela Jahudkova, Robert Monegro
Author-email: mbirger@redhat.com, mjahudko@readhat.com, rmonegro@redhat.com
License: GPLv3
Download-URL: https://github.com/redhat-aqe/kafka-logging-handler/archive/0.2.5.tar.gz
Platform: UNKNOWN
Classifier: Development Status :: 5 - Production/Stable
Classifier: Environment :: Console
Classifier: Intended Audience :: Developers
Classifier: License :: OSI Approved :: GNU General Public License v3 (GPLv3)
Classifier: Operating System :: OS Independent
Classifier: Programming Language :: Python :: 2.7
Classifier: Programming Language :: Python :: 3.6
Classifier: Topic :: System :: Logging
Classifier: Topic :: Software Development :: Libraries :: Python Modules
Requires-Dist: kafka-python
Requires-Dist: psutil
